{"geocoded_waypoints": [{"geocoder_status": "OK", "place_id": "ChIJhzeKfVQ0eUcRxPY0WADv3zs", "types": ["locality", "political"]}, {"geocoder_status": "OK", "place_id": "ChIJzzCrQVjafkcRLC4aqu02gsE", "types": ["locality", "political"]}], "routes": [{"bounds": {"northeast": {"lat": 45.602841, "lng": 12.170786}, "southwest": {"lat": 45.398765, "lng": 11.8761941}}, "copyrights": "Map data \u00a92019", "legs": [{"distance": {"text": "44.1 km", "value": 44133}, "duration": {"text": "46 mins", "value": 2733}, "end_address": "Padua, Province of Padua, Italy", "end_location": {"lat": 45.406418, "lng": 11.8767801}, "start_address": "31059 Zero Branco, Province of Treviso, Italy", "start_location": {"lat": 45.6011508, "lng": 12.1669293}, "steps": [{"distance": {"text": "0.2 km", "value": 183}, "duration": {"text": "1 min", "value": 28}, "end_location": {"lat": 45.602778, "lng": 12.1669372}, "html_instructions": "Head <b>north</b> on <b>Via Trento Trieste</b> toward <b>Via Noalese</b>/<b>SR515</b>", "polyline": {"points": "eniuGijgiAC?E?OAOA]Ck@C{AIs@AW@UJSF"}, "start_location": {"lat": 45.6011508, "lng": 12.1669293}, "travel_mode": "DRIVING"}, {"distance": {"text": "1.0 km", "value": 969}, "duration": {"text": "1 min", "value": 81}, "end_location": {"lat": 45.59861249999999, "lng": 12.1566064}, "html_instructions": "Turn <b>left</b> onto <b>Via Noalese</b>/<b>SR515</b>", "maneuver": "turn-left", "polyline": {"points": "kxiuGkjgiAKFbAbAZh@f@~@d@x@JHDFT^?@JPNZJTL\\JXJh@BRBP@N@J@XFnAJrC?RJxCFxA@V@LJx@DRLh@h@rA|@vBfB|Dz@jBj@pAFN@B@JDHP`@z@hBv@bB"}, "start_location": {"lat": 45.602778, "lng": 12.1669372}, "travel_mode": "DRIVING"}, {"distance": {"text": "0.4 km", "value": 359}, "duration": {"text": "1 min", "value": 32}, "end_location": {"lat": 45.5961465, "lng": 12.1595744}, "html_instructions": "Turn <b>left</b> onto <b>Via Guglielmo Marconi</b>", "maneuver": "turn-left", "polyline": {"points": "i~huGyieiAHGdDmElAcBf@q@bCeDJOTSFCDCFEBCBC@C"}, "start_location": {"lat": 45.59861249999999, "lng": 12.1566064}, "travel_mode": "DRIVING"}, {"distance": {"text": "0.5 km", "value": 482}, "duration": {"text": "1 min", "value": 35}, "end_location": {"lat": 45.5924779, "lng": 12.1625719}, "html_instructions": "At the roundabout, continue straight to stay on <b>Via Guglielmo Marconi</b>", "maneuver": "roundabout-right", "polyline": {"points": "}nhuGi|eiA@?@?@?@?@?@A@??A@??A@??A@A?A?A@??A?A?A?A?A?A?A?A?ADIDIHS`AwA`B{B^_@`@_@RMdCmApH_D"}, "start_location": {"lat": 45.5961465, "lng": 12.1595744}, "travel_mode": "DRIVING"}, {"distance": {"text": "0.1 km", "value": 101}, "duration": {"text": "1 min", "value": 11}, "end_location": {"lat": 45.5924385, "lng": 12.1638608}, "html_instructions": "Turn <b>left</b> to stay on <b>Via Guglielmo Marconi</b>", "maneuver": "turn-left", "polyline": {"points": "_xguGaofiAHkC?OAeB"}, "start_location": {"lat": 45.5924779, "lng": 12.1625719}, "travel_mode": "DRIVING"}, {"distance": {"text": "1.7 km", "value": 1692}, "duration": {"text": "2 mins", "value": 106}, "end_location": {"lat": 45.57768069999999, "lng": 12.1659106}, "html_instructions": "At the roundabout, take the <b>1st</b> exit onto <b>Via Peseggiana</b>", "maneuver": "roundabout-right", "polyline": {"points": "wwguGcwfiA@?@?@?@?@A@??A@?@A@A?A@??A@A?A?A@A?A?A?A?A?AT?L@L@@?F?nAD`@@^Bp@BX@fABD?t@BJ@r@DL@dBH`B@t@Ar@A`AAR@`@C`@A`ACx@A|ACTA`CCrDGzAC~@AzAEl@CBARCXITOfAu@@A`D{Bl@c@VOFE`@QjC?`BBv@BbEJdABRA`@GPIPMd@e@LUHW"}, "start_location": {"lat": 45.5924385, "lng": 12.1638608}, "travel_mode": "DRIVING"}, {"distance": {"text": "1.4 km", "value": 1442}, "duration": {"text": "2 mins", "value": 113}, "end_location": {"lat": 45.566689, "lng": 12.1695568}, "html_instructions": "<b>Via Peseggiana</b> turns slightly <b>left</b> and becomes <b>Via Spangaro</b>", "polyline": {"points": "o{duG}cgiAFe@LyA@QFu@B[Fk@DYLa@LQBCJKJEd@QXCz@GFAZCZCNA`@EnCSb@Eb@EfDg@RGNKJONYPo@Jy@RkBD_@BQLg@JQFIHGr@Yd@QBA\\KPEf@MRCN?l@Bb@DH?P@fBHN@jAJRBlALtDr@r@NNB`@H`ARlCd@B?bB^rAR"}, "start_location": {"lat": 45.57768069999999, "lng": 12.1659106}, "travel_mode": "DRIVING"}, {"distance": {"text": "0.5 km", "value": 512}, "duration": {"text": "1 min", "value": 37}, "end_location": {"lat": 45.5675555, "lng": 12.1631928}, "html_instructions": "At the roundabout, take the <b>1st</b> exit onto <b>Via Moglianese</b>/<b>SP39</b>", "maneuver": "roundabout-right", "polyline": {"points": "yvbuGwzgiA?B?@?@?B?@?@@B?@?@@B?@@@?@@@@@@@?@B@?@@?@?WtCOpAQhBEd@KfAI`AKlAIt@KdAARMlAK`AARSlCCTCVGpAGx@"}, "start_location": {"lat": 45.566689, "lng": 12.1695568}, "travel_mode": "DRIVING"}, {"distance": {"text": "0.6 km", "value": 650}, "duration": {"text": "1 min", "value": 47}, "end_location": {"lat": 45.5618558, "lng": 12.162673}, "html_instructions": "Turn <b>left</b> onto <b>Via Alessandro Volta</b>", "maneuver": "turn-left", "polyline": {"points": "g|buG}rfiAAVJDDBB?B@@?B?DA@?@A@A@?@ABCHAh@Cr@E|A?`ABjEDjC@f@@`@?h@@X?X?h@FpAT~B`@PDP@XB"}, "start_location": {"lat": 45.5675555, "lng": 12.1631928}, "travel_mode": "DRIVING"}, {"distance": {"text": "0.8 km", "value": 763}, "duration": {"text": "1 min", "value": 52}, "end_location": {"lat": 45.5551853, "lng": 12.161567}, "html_instructions": "At the roundabout, take the <b>1st</b> exit onto <b>Via Canove</b>", "maneuver": "roundabout-right", "polyline": {"points": "sxauGuofiA@??@@??@@?@@@?@?@?@??A@?f@HPF^HLBN?j@@zFVj@B|CLR?n@@j@B`GXvEJL@LBVFRLXRFFBHBL?FAF"}, "start_location": {"lat": 45.5618558, "lng": 12.162673}, "travel_mode": "DRIVING"}, {"distance": {"text": "0.5 km", "value": 511}, "duration": {"text": "1 min", "value": 38}, "end_location": {"lat": 45.5582094, "lng": 12.1567771}, "html_instructions": "Continue straight", "maneuver": "straight", "polyline": {"points": "}n`uGyhfiAK|@m@x@i@v@U`@KReAvBm@xAo@|Au@lBWn@KV_@z@QXGFEDQJK@G@EDGDc@f@WVY^MP"}, "start_location": {"lat": 45.5551853, "lng": 12.161567}, "travel_mode": "DRIVING"}, {"distance": {"text": "53 m", "value": 53}, "duration": {"text": "1 min", "value": 5}, "end_location": {"lat": 45.5581709, "lng": 12.1561441}, "html_instructions": "Keep <b>left</b>", "maneuver": "keep-left", "polyline": {"points": "yaauG{jeiACRCRAP@T@RDNFJ"}, "start_location": {"lat": 45.5582094, "lng": 12.1567771}, "travel_mode": "DRIVING"}, {"distance": {"text": "1.1 km", "value": 1124}, "duration": {"text": "1 min", "value": 68}, "end_location": {"lat": 45.5617612, "lng": 12.1430906}, "html_instructions": "Keep <b>right</b>", "maneuver": "keep-right", "polyline": {"points": "qaauG{feiABL@J@RAPC^Eb@Kj@]`B?B[|AIf@_@hB]lBKz@Kt@MnAEb@MnBIxAGlAOlDI|AEz@El@SjBKr@GZKl@c@fBm@|Bc@zAQl@Oj@W~@[dAGTWbA]~@]z@]n@S`@QHUFSB"}, "start_location": {"lat": 45.5581709, "lng": 12.1561441}, "travel_mode": "DRIVING"}, {"distance": {"text": "1.0 km", "value": 987}, "duration": {"text": "1 min", "value": 81}, "end_location": {"lat": 45.5572563, "lng": 12.1496075}, "html_instructions": "At the roundabout, take the <b>2nd</b> exit onto the <b>A4</b>/<b>E70</b> ramp to <b>Milano</b>", "maneuver": "roundabout-right", "polyline": {"points": "_xauGiubiAUGK?IBKBIFIHGJELAFCFANAN?NBPBLDNDJHHHHHDJBJ@HAJCHEHIHIDMDKLELINWRu@DOVy@\\sA^qADMj@uB@Cr@eCJ[T}@^wAPq@Nk@Ja@dAcEBGLe@Nm@Ja@BIRs@Pc@DIJULUJMBCLKNKVGFALCVAN?L@|@Bl@AB?h@G"}, "start_location": {"lat": 45.5617612, "lng": 12.1430906}, "travel_mode": "DRIVING"}, {"distance": {"text": "25.5 km", "value": 25484}, "duration": {"text": "15 mins", "value": 898}, "end_location": {"lat": 45.4195517, "lng": 11.9445611}, "html_instructions": "Merge onto <b>A4</b>/<b>E70</b><div style=\"font-size:0.9em\">Toll road</div>", "maneuver": "merge", "polyline": {"points": "{{`uGa~ciAx@FlCPfBN~@J@?jATvATv@R|@VlA\\|DdBhC`AhHvDxBhAfFfCjEzBhLbG^R`Bz@fClAtDhBxBx@nAd@dD`AxA\\vBb@^HrDf@@?~@HbAHf@DlADzADhBDZ?H?nBCV?vEU~DSbAIhBIB?b@A~@EdA?h@?F?lA@jADbBLv@HdC^RDb@HdATdAX|Cz@pA^XFFBND`Dv@n@LZFlARTDp@HF@p@FrAJB?xADz@BZ?H@lBCD?\\AH?BAN?bBKnAK^EpC[LA\\ERC~@KdBQ|CSd@CtAEzBAD?^?^?v@@hAFbBH`AHhD\\b@DnALnALXDh@F`DZvAHb@BPBtAD`CDhDClEKF?ZAfEKbFAtA?r@B|AFVBjBJhBRRBN@zG|@vAT~D`@z@BnADpA@@?bBC~AE~AGpCOrBKzAGr@C~BE`@?b@?jABjA@hAD`ADt@BzAL~BZrDl@vBd@VF`AVdBf@rAd@JBrAf@nCjA`Ab@xBjArE~BpGfD`@T~@d@xAv@j@VxAt@zDrBr@^j@ZhDnBrBrAtAbAf@^rAhAp@n@n@p@Z\\VXVZn@t@dAtARX@@?@TZf@t@lApBt@vAp@tAl@tA~@~BVn@BHXx@Vt@Vz@Nb@Pl@Rt@ZpAr@bDZzAZfBVxA`@fCPnAp@rEn@lEHj@f@hDT`Bb@|CrBpNRtAV`BN`A`@fCJj@Jn@Jh@b@`C^dBd@nBf@lB\\hA\\dABJh@zAv@rBXr@LVVj@j@jAh@fAd@x@^p@z@pAlAfBp@z@rBdCJJhCbCxBhB~@r@pBzAHFpA|@p@b@z@l@LHvA~@xBxAtA~@fCdBb@X|AdAvA|@`@Zb@XDBvBvAdEnC|CnBTNpDbClCfBVPfDzB^VjAv@jAx@xA`Ax@l@`@Xf@\\pB|AFDVTn@j@jBbBHJdAhA^`@~@fA`AjAJNTV^h@V^~@tAl@~@Xf@Xd@FHFNXd@Zl@JTFHVh@Zr@Vh@Th@P^HVb@bAJV\\z@Rn@f@tAb@tAZ`APl@Nl@d@bBZtAXxANp@Jb@DZRhATnAb@bCF^F\\D\\DVF`@?@Jp@Jt@RxAVnBRbBDTHl@NpAJv@DZ@P@@Fl@L~@J~@RzAHx@Jv@Hj@BR`@bDBN@NNhAD\\Hp@Hl@Fl@Hn@Hp@BLFf@Fh@Hp@L~@Jx@BRJr@Fn@Jp@Jz@LfABPHn@Hr@Lz@Jz@LhATfBDXLdAR|AR~ATnBRdB^tCHp@DZLdA?@NlALbA@BJ|@D^DTVtBThB?BD\\L~@Hn@Jv@Jt@Dd@Fh@Lx@B\\Jt@LfANlAPtAPvAFf@Fb@Ff@Fh@Hl@Hl@NpARzARdBX`Cf@`EVtBX|Bh@fEpBrPj@nEn@hFh@dEbAjIdBvNtDtZr@zFdApIT`BLfAxEb`@lB|OR`BHr@BTBTp@jFR~AH^j@vE\\rCd@vDxIrs@lAxJ~@vHxBlQdFta@LdAjEv]bC~RBRBPnAdKHn@p@tFHp@bC|R\\rCHp@|@dHfA`JBRBPPvATlBR~AHp@L`AD`@h@bEBPNnAHp@NnABPVtBNlANpABPRxA@F\\pCZdCXbCnAhKbBnNX`C\\xC`@dDVdBFj@Jn@b@dDJx@DZFd@@DtBjPj@jEBRBN?BFZ?BNhAn@hFXxBDd@@DNpA^|Cp@tFHp@BRbAbIp@lFTfBBN?B@BJ|@VtBVtBn@hF"}, "start_location": {"lat": 45.5572563, "lng": 12.1496075}, "travel_mode": "DRIVING"}, {"distance": {"text": "1.1 km", "value": 1106}, "duration": {"text": "2 mins", "value": 101}, "end_location": {"lat": 45.4173025, "lng": 11.9330073}, "html_instructions": "Take exit <b>Padova Est</b> toward <b>Padova Est</b>/<b>Padova Centro</b>", "maneuver": "ramp-right", "polyline": {"points": "e_ftGo|{gAJdC?l@@r@?DAb@A\\A\\ALATCPCTEXEVER?@ENGVIXOd@Qh@Od@Mb@Ql@Qj@ENMZITMf@CPAT?R?TBXD\\DNDLFPLVLRPRRNLFTJRFDBb@LB@JDLDd@NXH~@\\NFHDPLFDLLLPJLFLHNFNBDBJDNLr@@FRnAJbAJx@B\\?HB`@?hADp@@l@Fp@Fl@Ff@BPRtAVfABNH^"}, "start_location": {"lat": 45.4195517, "lng": 11.9445611}, "travel_mode": "DRIVING"}, {"distance": {"text": "19 m", "value": 19}, "duration": {"text": "1 min", "value": 3}, "end_location": {"lat": 45.4172847, "lng": 11.9327696}, "html_instructions": "Keep <b>right</b> at the fork to continue toward <b>Via S. Marco</b>", "maneuver": "fork-right", "polyline": {"points": "cqetGitygABn@"}, "start_location": {"lat": 45.4173025, "lng": 11.9330073}, "travel_mode": "DRIVING"}, {"distance": {"text": "0.4 km", "value": 423}, "duration": {"text": "1 min", "value": 40}, "end_location": {"lat": 45.4195705, "lng": 11.9322249}, "html_instructions": "Keep <b>right</b>, follow signs for <b>Ponte di Brenta</b>", "maneuver": "keep-right", "polyline": {"points": "_qetGyrygAELADAF?H?\\CTABAFABAFKVUXo@z@ED[`@GFSVu@`A]f@OPOLIFKBK@K?E?EAIECCECEECECCCGEKAGEOIk@_@wBWaB"}, "start_location": {"lat": 45.4172847, "lng": 11.9327696}, "travel_mode": "DRIVING"}, {"distance": {"text": "0.4 km", "value": 377}, "duration": {"text": "1 min", "value": 28}, "end_location": {"lat": 45.4212032, "lng": 11.9363891}, "html_instructions": "Keep <b>left</b> at the fork, follow signs for <b>Vigonza</b> and merge onto <b>Via S. Marco</b>", "maneuver": "fork-left", "polyline": {"points": "i_ftGkoygAKUI[Gc@ScAMy@EQAG?CCEIQEq@Ii@G_@Kc@Ma@EISi@GQISIUIUOc@EMSi@Wo@_@y@[i@"}, "start_location": {"lat": 45.4195705, "lng": 11.9322249}, "travel_mode": "DRIVING"}, {"distance": {"text": "1.3 km", "value": 1273}, "duration": {"text": "2 mins", "value": 98}, "end_location": {"lat": 45.4166509, "lng": 11.9224319}, "html_instructions": "At the roundabout, take the <b>3rd</b> exit and stay on <b>Via S. Marco</b>", "maneuver": "roundabout-right", "polyline": {"points": "oiftGmizgA?A?A?A?A?AAA?A?A?AA??A?AA??AAAAAAAA?AAA?A?A?A?A?A@A??@A?A@A@?@A@?@?@A??@?@?@?@?@?@?@?@?@?@@@?@?@@@?@@@@@?@@??@@?@??@@?@?@?@?@?j@P^x@Vn@Rh@DLNb@HTHTHRFPRh@DHL`@Jb@F^Hh@Dp@Dj@Fp@@FDb@JdA\\xBj@~CRnAd@fCF^r@zDJr@R|@`@vAZfAf@jB\\lAf@nBb@|AFRRt@Pj@tBrHRv@Rr@?H?B@R@J?F?H?HCV"}, "start_location": {"lat": 45.4212032, "lng": 11.9363891}, "travel_mode": "DRIVING"}, {"distance": {"text": "0.2 km", "value": 216}, "duration": {"text": "1 min", "value": 21}, "end_location": {"lat": 45.4156369, "lng": 11.920241}, "html_instructions": "At the roundabout, take the <b>2nd</b> exit onto <b>Via S. Marco</b>/<b>Via Venezia</b>", "maneuver": "roundabout-right", "polyline": {"points": "ametGerwgACNAB?F@L?B@B@@@B@BB@@B@@BBDDD?F@LHDBDBDFDJJVHNXhAr@dCJ\\Nh@"}, "start_location": {"lat": 45.4166509, "lng": 11.9224319}, "travel_mode": "DRIVING"}, {"distance": {"text": "0.9 km", "value": 940}, "duration": {"text": "1 min", "value": 68}, "end_location": {"lat": 45.4116151, "lng": 11.909657}, "html_instructions": "Continue straight onto <b>Via Venezia</b>", "maneuver": "straight", "polyline": {"points": "wfetGodwgA\\dA\\nA`@xAr@fCtA~EPj@Pl@f@hBHT@FBHFRRx@l@tB@FDPPj@HVFVFVb@zAV|@|@|Ct@lCTx@J\\f@fBFd@FTvAjF"}, "start_location": {"lat": 45.4156369, "lng": 11.920241}, "travel_mode": "DRIVING"}, {"distance": {"text": "0.7 km", "value": 659}, "duration": {"text": "1 min", "value": 65}, "end_location": {"lat": 45.4087508, "lng": 11.9023439}, "html_instructions": "At the roundabout, take the <b>2nd</b> exit and stay on <b>Via Venezia</b>", "maneuver": "roundabout-right", "polyline": {"points": "smdtGkbugA?@A@?@A??@?@?@A??@?@?@?@?@?@?@?@@@?@X|@FPf@fBZfAPl@f@~AzEbPp@lB@@NTzArF`@zABN"}, "start_location": {"lat": 45.4116151, "lng": 11.909657}, "travel_mode": "DRIVING"}, {"distance": {"text": "0.5 km", "value": 475}, "duration": {"text": "1 min", "value": 66}, "end_location": {"lat": 45.4059187, "lng": 11.9010695}, "html_instructions": "At the roundabout, take the <b>4th</b> exit onto <b>Via Ludovico Ariosto</b><div style=\"font-size:0.9em\">Go through 1 roundabout</div>", "maneuver": "roundabout-right", "polyline": {"points": "u{ctGstsgAIBGDEFEDGFGDOFIDCHEJAFAD?HAH@JDR@HBFBFB@D@B?F?FADEHEBCj@g@LWJQRDD@HDBBLFTLf@Xb@XTLNH@?DDFDD@D@D@D?D?HE~@LZDj@H`@Fb@D^D^D"}, "start_location": {"lat": 45.4087508, "lng": 11.9023439}, "travel_mode": "DRIVING"}, {"distance": {"text": "71 m", "value": 71}, "duration": {"text": "1 min", "value": 7}, "end_location": {"lat": 45.4052838, "lng": 11.9009746}, "html_instructions": "Continue onto <b>Ponte Ariosto</b>", "polyline": {"points": "_jctGulsgAPBPBx@JN?B?L?"}, "start_location": {"lat": 45.4059187, "lng": 11.9010695}, "travel_mode": "DRIVING"}, {"distance": {"text": "0.2 km", "value": 250}, "duration": {"text": "1 min", "value": 27}, "end_location": {"lat": 45.4031285, "lng": 11.9000795}, "html_instructions": "At the roundabout, take the <b>2nd</b> exit onto <b>Via Ludovico Ariosto</b>", "maneuver": "roundabout-right", "polyline": {"points": "_fctGalsgA@??@@?@?@?@?@?@AfErAhCx@lAb@"}, "start_location": {"lat": 45.4052838, "lng": 11.9009746}, "travel_mode": "DRIVING"}, {"distance": {"text": "0.9 km", "value": 930}, "duration": {"text": "2 mins", "value": 110}, "end_location": {"lat": 45.40180760000001, "lng": 11.8893678}, "html_instructions": "At the roundabout, take the <b>1st</b> exit onto <b>Via Gattamelata</b><div style=\"font-size:0.9em\">Go through 1 roundabout</div>", "maneuver": "roundabout-right", "polyline": {"points": "qxbtGofsgA?@@??@@@@@CLAPOxA?ZEb@QrBMrAOz@I`@Mj@Of@[dA[~@GXCPCLAN?T?XB\\@RHt@h@|CLn@ZfBA??@A??@?@A??@?@?@A@?@?@@??@?@?@?@@??@?@@??@@?@@@?@?@?@??A@?Pt@HVTn@\\x@dA~BRf@FJ?L?@?@XdA`AxDFT\\nANr@DRDv@"}, "start_location": {"lat": 45.4031285, "lng": 11.9000795}, "travel_mode": "DRIVING"}, {"distance": {"text": "0.4 km", "value": 423}, "duration": {"text": "1 min", "value": 61}, "end_location": {"lat": 45.39875929999999, "lng": 11.8864392}, "html_instructions": "At the roundabout, take the <b>2nd</b> exit and stay on <b>Via Gattamelata</b>", "maneuver": "roundabout-right", "polyline": {"points": "ipbtGqcqgACL?@A@?@?@?@?@?@?@?@?@@@?@?@@@?@@@@@?@@??@@?@@@?@?@?@?@?@?@?LTFJPTHJXZB@B@F?^V~CvBhAv@h@`@r@f@t@r@X\\V\\^l@"}, "start_location": {"lat": 45.40180760000001, "lng": 11.8893678}, "travel_mode": "DRIVING"}, {"distance": {"text": "0.2 km", "value": 170}, "duration": {"text": "1 min", "value": 34}, "end_location": {"lat": 45.4000198, "lng": 11.8852931}, "html_instructions": "At the roundabout, take the <b>1st</b> exit onto <b>Via Jacopo Facciolati</b>", "maneuver": "roundabout-right", "polyline": {"points": "g}atGgqpgA?@A??@A??@?@A??@?@?@?@?@?@?@?@k@n@m@f@qAz@iAx@"}, "start_location": {"lat": 45.39875929999999, "lng": 11.8864392}, "travel_mode": "DRIVING"}, {"distance": {"text": "0.2 km", "value": 234}, "duration": {"text": "1 min", "value": 44}, "end_location": {"lat": 45.4016916, "lng": 11.8837932}, "html_instructions": "At the roundabout, take the <b>2nd</b> exit onto <b>Piazzale Pontecorvo</b>", "maneuver": "roundabout-right", "polyline": {"points": "cebtGajpgA?AA??AA??AA??AA?A?A?A?A??@A??@A??@A??@?@A??@?@?@?@?@?@?@MCEAQPCH[x@CJGLKLIHMJOLEFCHg@T}@j@]Ra@V"}, "start_location": {"lat": 45.4000198, "lng": 11.8852931}, "travel_mode": "DRIVING"}, {"distance": {"text": "0.1 km", "value": 98}, "duration": {"text": "1 min", "value": 20}, "end_location": {"lat": 45.4024941, "lng": 11.8832767}, "html_instructions": "Continue onto <b>Via S. Francesco</b>", "polyline": {"points": "qobtGu`pgAg@Z_@TwAr@"}, "start_location": {"lat": 45.4016916, "lng": 11.8837932}, "travel_mode": "DRIVING"}, {"distance": {"text": "0.2 km", "value": 199}, "duration": {"text": "1 min", "value": 42}, "end_location": {"lat": 45.4019556, "lng": 11.8808685}, "html_instructions": "<b>Via S. Francesco</b> turns <b>left</b> and becomes <b>Via M. Cesarotti</b>", "polyline": {"points": "qtbtGo}ogAAH?F?B@HDPZvALh@T`AF^Bf@Dl@Dh@J~@?J"}, "start_location": {"lat": 45.4024941, "lng": 11.8832767}, "travel_mode": "DRIVING"}, {"distance": {"text": "71 m", "value": 71}, "duration": {"text": "1 min", "value": 18}, "end_location": {"lat": 45.4018179, "lng": 11.8799761}, "html_instructions": "Continue onto <b>Piazza del Santo</b>", "polyline": {"points": "gqbtGmnogALvAD`@Fv@"}, "start_location": {"lat": 45.4019556, "lng": 11.8808685}, "travel_mode": "DRIVING"}, {"distance": {"text": "0.2 km", "value": 172}, "duration": {"text": "1 min", "value": 41}, "end_location": {"lat": 45.4032502, "lng": 11.8791555}, "html_instructions": "Turn <b>right</b> onto <b>Via del Santo</b><div style=\"font-size:0.9em\">Closed Mon\u2013Fri 8:00 AM \u2013 8:00 PM</div>", "maneuver": "turn-right", "polyline": {"points": "kpbtG{hogAi@Pk@Tc@Ta@N_@TKDa@Vs@`@"}, "start_location": {"lat": 45.4018179, "lng": 11.8799761}, "travel_mode": "DRIVING"}, {"distance": {"text": "71 m", "value": 71}, "duration": {"text": "1 min", "value": 20}, "end_location": {"lat": 45.4027221, "lng": 11.8786352}, "html_instructions": "Turn <b>left</b> onto <b>Via Rudena</b><div style=\"font-size:0.9em\">Entering toll zone</div>", "maneuver": "turn-left", "polyline": {"points": "iybtGwcogAhBfB"}, "start_location": {"lat": 45.4032502, "lng": 11.8791555}, "travel_mode": "DRIVING"}, {"distance": {"text": "0.2 km", "value": 222}, "duration": {"text": "1 min", "value": 67}, "end_location": {"lat": 45.4033892, "lng": 11.876246}, "html_instructions": "Turn <b>right</b> onto <b>Via Santa Chiara</b><div style=\"font-size:0.9em\">Leaving toll zone</div>", "maneuver": "turn-right", "polyline": {"points": "_vbtGo`ogAk@pB?BA?A@A?A?A?CAA?A?A?A@?@ABCDADCJABIXQt@IZGXG\\Mt@NF?@@??@@@?B@D?DAJAPCl@"}, "start_location": {"lat": 45.4027221, "lng": 11.8786352}, "travel_mode": "DRIVING"}, {"distance": {"text": "0.3 km", "value": 337}, "duration": {"text": "1 min", "value": 87}, "end_location": {"lat": 45.4061723, "lng": 11.8778065}, "html_instructions": "Turn <b>right</b> onto <b>Riviera Tito Livio</b><div style=\"font-size:0.9em\">Entering toll zone</div>", "maneuver": "turn-right", "polyline": {"points": "ezbtGqqngAMJK?EAGACCWQeA{@QIg@WQIuAe@u@]k@YaAg@SMGGQKm@Y"}, "start_location": {"lat": 45.4033892, "lng": 11.876246}, "travel_mode": "DRIVING"}, {"distance": {"text": "85 m", "value": 85}, "duration": {"text": "1 min", "value": 33}, "end_location": {"lat": 45.406418, "lng": 11.8767801}, "html_instructions": "Turn <b>left</b> onto <b>Via S. Francesco</b>", "maneuver": "turn-left", "polyline": {"points": "qkctGi{ngAq@lE"}, "start_location": {"lat": 45.4061723, "lng": 11.8778065}, "travel_mode": "DRIVING"}], "traffic_speed_entry": [], "via_waypoint": []}], "overview_polyline": {"points": "eniuGijgiAcGWm@L_@N~AlBlAxBf@r@t@`B^hBLdC^zKTrBv@|BdDtHpBpEtA`Dv@bBHGrFqHlE{FXQHGB?FEDWxD}F`A_AxC{ApH_DHkCAuBD?BAFEDS|Mb@jGJjDEbT]lEMl@M|AeApEaD^U`@QjC?xCFhGNt@Ib@Wr@{@P}@Z}DLeAZs@`Ag@vIq@bG{@Z[`@iAh@wEj@kAzBy@|AWdIf@fItAtFbAvDx@?HFRFFSvC_BtPaAdMIpAPHL@\\M|FE`LHfCHtF~@\\D@@F@|AXrQp@rOj@rAl@Nf@MdAwApBuCfGiCrG_AbBk@T}AdBQd@Ed@PdAD~@s@pEeArFcAnHe@zHe@tJs@hFsEvPu@bC{@jBe@j@i@Ja@GUFa@j@In@Fn@^n@j@Hh@]JYZO`AwCnBiHdD{L|CcLj@cAx@c@|@G|BBbB?tF`@dFv@tBj@jGbChC`AhHvD`JpEvVnM|HvDhE~A~F~AvCl@xHz@zHVlDCdQ}@lDGjEFtH|@pMfDzH`B`CXlFTxCAz@CdJy@~BW~Jo@`EAfH\\jTrBlGRzKQjLMhCBjIj@vKxAzFd@`DFdHQtKg@pGAlGPzEh@jHrArGlBpHzC`ShK~GjDdM~GdI`GtCxC`FvGbChE~AjDtBrFpAbE~BfKzFp_@vG~c@zA`IhClJ~BnGzBvEnEdHdD`EtCnCtH`GlExCjTxNhk@r_@xDvCjFdFlDdElCvDrDpGhDvHvD~KjB`It@zD|AjJvBjPfDpXpCbUvK~|@f^jwCpdAhpIxW|wBlSn`BfA~IJrDAzB_@nDwA|Ew@dC]dBH`B`@fA`A~@rAd@vDrAt@r@d@z@ZtAl@tE^rIv@vELn@A|@Ct@Id@sAtB}@fAsBhCm@Lm@_@Qk@mA{G{@{EMWO{Ag@oBiA_DmBoECQKIULB`@HFF?j@P^x@j@xADLb@nAj@xAj@nCTvCzAbKtBrL|ApGpCfKjEbPEfBLh@n@^\\n@bB|FzGzUnHzW~BlIfBhHCBANfBhGfI~WnCfJERMLe@ZUb@Ad@Nl@TBZQx@_AJQRDNFPJvBnAv@ZNEzARpC\\~CXB@F?bLpDBDkA|LoBtH@|AbAvGXhBCD?PHFD?pAtD`B`EzAbGz@lD@fAAHDRLFF?p@bAh@^rHhFhBzAp@z@^n@A?ABAB?H?ByAvA{CrBCAACE?IFAH?BMAWN_@bAa@p@g@j@eDlBaDnBnAjGv@|J{ClAaCtAhBfBk@pBABG@MDy@`DUrANHBB@NC\\Cl@MJQAKEwCoBiEgBoBiAm@Yq@lE"}, "summary": "A4/E70", "warnings": [], "waypoint_order": []}, {"bounds": {"northeast": {"lat": 45.6011508, "lng": 12.2754858}, "southwest": {"lat": 45.3987698, "lng": 11.8762144}}, "copyrights": "Map data \u00a92019", "legs": [{"distance": {"text": "54.1 km", "value": 54052}, "duration": {"text": "52 mins", "value": 3111}, "end_address": "Padua, Province of Padua, Italy", "end_location": {"lat": 45.406418, "lng": 11.8767801}, "start_address": "31059 Zero Branco, Province of Treviso, Italy", "start_location": {"lat": 45.6011508, "lng": 12.1669293}, "steps": [{"distance": {"text": "16 m", "value": 16}, "duration": {"text": "1 min", "value": 2}, "end_location": {"lat": 45.6010379, "lng": 12.1670496}, "html_instructions": "Head <b>southeast</b> on <b>Via Trento Trieste</b> toward <b>Via Martiri della Libert\u00e0</b>", "polyline": {"points": "eniuGijgiA@?@A@??A?ABAJO"}, "start_location": {"lat": 45.6011508, "lng": 12.1669293}, "travel_mode": "DRIVING"}, {"distance": {"text": "0.9 km", "value": 907}, "duration": {"text": "1 min", "value": 70}, "end_location": {"lat": 45.6001322, "lng": 12.1786044}, "html_instructions": "<b>Via Trento Trieste</b> turns slightly <b>left</b> and becomes <b>Via 1\u00b0 Maggio</b>/<b>SP65</b><div style=\"font-size:0.9em\">Continue to follow Via 1\u00b0 Maggio</div>", "polyline": {"points": "omiuGakgiADMDOBOJwAJeA?E@GFk@D[BW?M@k@BkADeBLeGDyAJsBTkJLkFDcEJgEJmEJyA"}, "start_location": {"lat": 45.6010379, "lng": 12.1670496}, "travel_mode": "DRIVING"}, {"distance": {"text": "0.2 km", "value": 184}, "duration": {"text": "1 min", "value": 13}, "end_location": {"lat": 45.5991537, "lng": 12.1804645}, "html_instructions": "Slight <b>right</b> onto <b>Via John Kennedy</b>/<b>SP65</b>", "maneuver": "turn-slight-right", "polyline": {"points": "ygiuGgsiiAb@}AJ]BI?MVm@LO|AiCDIDM"}, "start_location": {"lat": 45.6001322, "lng": 12.1786044}, "travel_mode": "DRIVING"}, {"distance": {"text": "0.1 km", "value": 141}, "duration": {"text": "1 min", "value": 8}, "end_location": {"lat": 45.5982529, "lng": 12.1817454}, "html_instructions": "Continue onto <b>Via Kennedy</b>", "polyline": {"points": "uaiuG{~iiAl@aAv@oAlAoB"}, "start_location": {"lat": 45.5991537, "lng": 12.1804645}, "travel_mode": "DRIVING"}, {"distance": {"text": "2.7 km", "value": 2683}, "duration": {"text": "2 mins", "value": 140}, "end_location": {"lat": 45.5910709, "lng": 12.2123587}, "html_instructions": "Continue onto <b>SP65</b>", "polyline": {"points": "a|huG}fjiAfAgBjCcEfDkFnLcRXm@HSLe@BOHa@Hs@JkADm@?AZoG`@cHDm@`@}GNmBLm@d@oBRu@H[j@mBVy@Ng@\\sARkAv@mG?CPkBBYFg@fA{ILcAFe@@KNoA^aDRiBX{B?EdAkJBSXcCTiBL_BFiA?K?aAGsAKs@Kw@YqAQi@e@qA[y@m@cBQo@I_@Km@Ec@Jq@"}, "start_location": {"lat": 45.5982529, "lng": 12.1817454}, "travel_mode": "DRIVING"}, {"distance": {"text": "1.7 km", "value": 1738}, "duration": {"text": "2 mins", "value": 102}, "end_location": {"lat": 45.581975, "lng": 12.2270205}, "html_instructions": "At the roundabout, take the <b>2nd</b> exit", "maneuver": "roundabout-right", "polyline": {"points": "eoguGgfpiA@A@ABA@A@C@A@C@A@C@C@C?E@C@C?A?C@C?C?C?C?C?CAC?C?CAA?CACZu@bA{A`@s@@C`@w@`@aA^sALo@FWBWHs@Bo@@O@c@?S?_@Ac@EaAMqBCc@Ce@?M?S@e@Ba@Fe@Lc@Nc@Vg@TY?ALKNM`@Qj@QDC`@MTK`@UZ[PW@AP_@N_@H]Fa@D]@k@?a@Am@A[Cu@?s@?S@YBi@Fi@Jq@J]H_@Pe@Ne@Vc@Vc@V]X]`@a@d@_@t@e@t@Yb@Mb@MlASdAQ\\GVGZMTMZQRSb@c@^g@b@g@`@e@ZUXQXKVGp@Mj@Gj@Ah@A"}, "start_location": {"lat": 45.5910709, "lng": 12.2123587}, "travel_mode": "DRIVING"}, {"distance": {"text": "1.5 km", "value": 1488}, "duration": {"text": "2 mins", "value": 94}, "end_location": {"lat": 45.5733425, "lng": 12.2280585}, "html_instructions": "At the roundabout, take the <b>2nd</b> exit onto <b>Via Zero Branco</b>", "maneuver": "roundabout-right", "polyline": {"points": "kveuG{asiA@B?B@D@B@B@B@@@B@BB@@@@@B@B?@@B?B?@?BA@AB?@ABCBA@C@C@A@C@C?E@C?C@C?E?C?CAE?CAC?CACACCEL[J]FW^y@V_@ZUZSb@Sh@Sf@OJENI\\SdAw@j@e@vBcBTO\\Ud@Yd@Q`@Oh@KxBYhHs@zGq@dBQJAFAPCfAKNA\\CXBXDFBJDTPTVRZNf@Jb@B`@?^?T?DA\\Gh@CTGd@WxASv@OZKLCDWR_@LQFw@E"}, "start_location": {"lat": 45.581975, "lng": 12.2270205}, "travel_mode": "DRIVING"}, {"distance": {"text": "0.5 km", "value": 515}, "duration": {"text": "1 min", "value": 41}, "end_location": {"lat": 45.5736113, "lng": 12.2344031}, "html_instructions": "At the roundabout, take the <b>1st</b> exit and stay on <b>Via Zero Branco</b>", "maneuver": "roundabout-right", "polyline": {"points": "k`duGkhsiAEICGEEGGECGCGCGAK_@GQEe@?Q@_E@mD?sA@G?U?S@gB@{A@oBBW@[?q@@y@?_@By@?Q@g@"}, "start_location": {"lat": 45.5733425, "lng": 12.2280585}, "travel_mode": "DRIVING"}, {"distance": {"text": "0.7 km", "value": 700}, "duration": {"text": "1 min", "value": 48}, "end_location": {"lat": 45.5731995, "lng": 12.2431033}, "html_instructions": "At the roundabout, take the <b>2nd</b> exit onto <b>Circonvallazione Nord</b>", "maneuver": "roundabout-right", "polyline": {"points": "abduG_ptiAHGHGFKFMDMBQ@O@Q?A?A?A?A?A?A?A?AAICICICIEGEGEGEEGiACMFg@LaBLwBDgALwFFiMPeL"}, "start_location": {"lat": 45.5736113, "lng": 12.2344031}, "travel_mode": "DRIVING"}, {"distance": {"text": "1.7 km", "value": 1673}, "duration": {"text": "2 mins", "value": 96}, "end_location": {"lat": 45.5688239, "lng": 12.2613561}, "html_instructions": "At the roundabout, take the <b>2nd</b> exit and stay on <b>Circonvallazione Nord</b>", "maneuver": "roundabout-right", "polyline": {"points": "o_duGkfviAHAHCHEFIDKDK@O@MAMAMEMEIGIIGICGA@qFTwVPsPDeDNiKDwCFoBH}APwAPeAJg@H_@\\mA\\cAb@y@b@w@`@m@V[V[d@k@`@a@n@k@vCeCvC_Cf@Sp@S"}, "start_location": {"lat": 45.5731995, "lng": 12.2431033}, "travel_mode": "DRIVING"}, {"distance": {"text": "0.8 km", "value": 848}, "duration": {"text": "1 min", "value": 52}, "end_location": {"lat": 45.5681997, "lng": 12.2712283}, "html_instructions": "At the roundabout, take the <b>2nd</b> exit", "maneuver": "roundabout-right", "polyline": {"points": "cdcuGoxyiAFJJFHBJ@L?JCHEJCBIDGBGDG@IBG@I@K@MAOAOAMEMEKGKIGBqAFsAFg@\\yCRqBLeBHiADkADqBBeC?_BCgB?CCwAGyAIyAOcCCc@WkDAS"}, "start_location": {"lat": 45.5688239, "lng": 12.2613561}, "travel_mode": "DRIVING"}, {"distance": {"text": "3.2 km", "value": 3204}, "duration": {"text": "2 mins", "value": 120}, "end_location": {"lat": 45.5413539, "lng": 12.2736742}, "html_instructions": "Merge onto <b>A27</b> via the ramp to <b>Venezia</b>", "maneuver": "ramp-right", "polyline": {"points": "g`cuGev{iA@_@?W?[Cs@AQ?GA[?M?q@?A@k@@G@g@Bg@@U@MDY@GDQFUHYHOBEFMPSPSPOLIJEDCNEJCDAPCJ?@AH?F?\\Bx@DL?j@Bd@?hAEpH^~DT`@DH?ZBj@DtCN|G\\b@BF@jDPXBP@H?jEVZ@rEVpAFb@B^B`GZ`FXpDRfAH|BJrCNl@Dj@B|@FnBJvBLfBJlBJtADfABV@`@?R@nBA~BGf@Cb@Cv@GpCU~AQ|AWVGlAW|Bq@hBi@DCjA]"}, "start_location": {"lat": 45.5681997, "lng": 12.2712283}, "travel_mode": "DRIVING"}, {"distance": {"text": "1.0 km", "value": 967}, "duration": {"text": "1 min", "value": 47}, "end_location": {"lat": 45.5330162, "lng": 12.2745524}, "html_instructions": "Take exit <b>Per Tangenziale</b> toward <b>Venezia</b>/<b>Milano</b>/<b>A13</b>/<b>Padova</b>/<b>Bologna</b>", "maneuver": "ramp-right", "polyline": {"points": "mx}tGme|iAPBFAD?b@QdDeAlBo@~FqBt@SrAc@p@S`@Id@Kf@Gj@Cx@Ef@?r@?R@xADt@BJ@L?r@@^ER?P?V@VDXDD@HBPFRNRL^^TXZb@FFTP"}, "start_location": {"lat": 45.5413539, "lng": 12.2736742}, "travel_mode": "DRIVING"}, {"distance": {"text": "7.9 km", "value": 7938}, "duration": {"text": "6 mins", "value": 372}, "end_location": {"lat": 45.47763639999999, "lng": 12.2155188}, "html_instructions": "Merge onto <b>Tangenziale di Mestre</b>/<b>A57</b>", "maneuver": "merge", "polyline": {"points": "kd|tG}j|iA~F`NNZdAdCl@pA@Dx@jBpA|CfCxFVl@Xr@x@fBTh@|@pBpA|CnApCDLjBfE|B`FhA`CzBlEvCtF~@bBp@lAh@`AxAdC?@j@~@t@nAHLvDrGhFzIHNHNj@`AdAhBfAjBrAxB`AhBtDvGbAnBXj@FLFLHLjE`JpApCd@nAx@jBDLh@nAZr@N^@DLVdAdCf@fAj@hAR^DHDHJPHNzC|FpCdFj@hAT`@rAfCLVNVTd@@?\\n@LTLTp@hAt@dAPTf@j@b@b@LLTRTPd@^f@^XRTL^TpAt@tCzATJTNjCpAjEzBRJ~BnAbClANHLFfB~@^Pd@VNHNJzB`AHDt@X`A\\tAb@b@J`@JlCr@|Ab@h@LzCv@x@Vb@NLDRHRHTJ~@d@p@\\RLd@X~AhAj@d@NNVXRPTTZ^Z`@Z^NRhAzApAhBJLtBtC|AvBjBdC\\f@DFX`@|ChEv@dALPV\\RVBDV\\@??@RTJN^b@f@l@`A`Aj@h@RP`@\\l@f@v@h@n@b@|@f@p@^PFhAf@v@XjA`@vA^xBd@|@Rh@J`B\\bARHB|@RtEhAvBd@vBd@`ARb@J`@JTFRFh@Pd@Ph@P`@PZNZNjCnA`@TXNd@V^P`CjAj@X~@b@|@d@`Af@lAn@"}, "start_location": {"lat": 45.5330162, "lng": 12.2745524}, "travel_mode": "DRIVING"}, {"distance": {"text": "11.3 km", "value": 11296}, "duration": {"text": "7 mins", "value": 432}, "end_location": {"lat": 45.4472738, "lng": 12.0789832}, "html_instructions": "Continue onto <b>Tangenziale di Mestre</b>/<b>A57</b><div style=\"font-size:0.9em\">Partial toll road</div>", "polyline": {"points": "gjqtG_zpiA~@d@xBhATJZRVNVPXRNLNNPNNNPPTXRVJNJNNTPZNVLTJTJRP`@N\\Pf@L\\HZPh@VdAFTH^F\\F`@FZDZD\\D^DXBVBZBj@B`@HnALtBFjAF|@JnABd@@LDb@BTFp@JbARlBNpATdBVxB@Fh@dEf@xDb@jDf@dE~@lHZzBZrBTxAJv@Lv@Fl@`@lEDn@l@vFNzAFj@D\\NbADT@HZhBFZ\\vBLr@TlADZBVXzBTbBvA`Mf@bE@Bb@xDVlBp@pFfAbJFd@`AhIBP@@BTf@hE\\rC~@tH`BzMR`BFn@BPJr@h@nE^|Cf@|Dt@lGfA`JFf@@FBVxAxLp@lF`B~Mf@~DfA|IrBzPnB~Or@fGpAfK`@dDh@fE|@tHz@~GpAvKp@rFpArKJx@hAjJDRp@tF`@dDf@dEv@rGPzAr@|FJn@XfCfBxNv@nGnAhKNfAf@bEHj@z@jHDZPtAZbCHv@DXRbBR`B\\pChB~NhAnJBN|@pHdArIThBtB`Q~ArMd@~DHh@|ApMFh@ThBHt@Jt@NnAD\\PtAF`@j@vEHh@TrBLdATpBF`@DXFd@D`@PvAXfCX~BDf@Dn@L|AHbABb@Fp@Fl@Jx@LbAFj@PtAL`AHt@Lz@@HNpA@PHj@J|@D\\D`@B^B\\@T@X?V?NA^A^GdACVEb@AXCd@Cf@A`@ATBp@@V@V@NBNBP@LF\\HZLf@HXf@zAt@rB^dA^pARr@J^Tx@DNb@nBJj@BLPfAPfAF\\H\\DNDFFJ"}, "start_location": {"lat": 45.47763639999999, "lng": 12.2155188}, "travel_mode": "DRIVING"}, {"distance": {"text": "10.9 km", "value": 10933}, "duration": {"text": "6 mins", "value": 373}, "end_location": {"lat": 45.4195517, "lng": 11.9445611}, "html_instructions": "Merge onto <b>A4</b>/<b>E70</b><div style=\"font-size:0.9em\">Toll road</div>", "maneuver": "merge", "polyline": {"points": "mlktGsdvhAVnBRbBDTHl@NpAJv@DZ@P@@Fl@L~@J~@RzAHx@Jv@Hj@BR`@bDBN@NNhAD\\Hp@Hl@Fl@Hn@Hp@BLFf@Fh@Hp@L~@Jx@BRJr@Fn@Jp@Jz@LfABPHn@Hr@Lz@Jz@LhATfBDXLdAR|AR~ATnBRdB^tCHp@DZLdA?@NlALbA@BJ|@D^DTVtBThB?BD\\L~@Hn@Jv@Jt@Dd@Fh@Lx@B\\Jt@LfANlAPtAPvAFf@Fb@Ff@Fh@Hl@Hl@NpARzARdBX`Cf@`EVtBX|Bh@fEpBrPj@nEn@hFh@dEbAjIdBvNtDtZr@zFdApIT`BLfAxEb`@lB|OR`BHr@BTBTp@jFR~AH^j@vE\\rCd@vDxIrs@lAxJ~@vHxBlQdFta@LdAjEv]bC~RBRBPnAdKHn@p@tFHp@bC|R\\rCHp@|@dHfA`JBRBPPvATlBR~AHp@L`AD`@h@bEBPNnAHp@NnABPVtBNlANpABPRxA@F\\pCZdCXbCnAhKbBnNX`C\\xC`@dDVdBFj@Jn@b@dDJx@DZFd@@DtBjPj@jEBRBN?BFZ?BNhAn@hFXxBDd@@DNpA^|Cp@tFHp@BRbAbIp@lFTfBBN?B@BJ|@VtBVtBn@hF"}, "start_location": {"lat": 45.4472738, "lng": 12.0789832}, "travel_mode": "DRIVING"}, {"distance": {"text": "1.1 km", "value": 1106}, "duration": {"text": "2 mins", "value": 101}, "end_location": {"lat": 45.4173025, "lng": 11.9330073}, "html_instructions": "Take exit <b>Padova Est</b> toward <b>Padova Est</b>/<b>Padova Centro</b>", "maneuver": "ramp-right", "polyline": {"points": "e_ftGo|{gAJdC?l@@r@?DAb@A\\A\\ALATCPCTEXEVER?@ENGVIXOd@Qh@Od@Mb@Ql@Qj@ENMZITMf@CPAT?R?TBXD\\DNDLFPLVLRPRRNLFTJRFDBb@LB@JDLDd@NXH~@\\NFHDPLFDLLLPJLFLHNFNBDBJDNLr@@FRnAJbAJx@B\\?HB`@?hADp@@l@Fp@Fl@Ff@BPRtAVfABNH^"}, "start_location": {"lat": 45.4195517, "lng": 11.9445611}, "travel_mode": "DRIVING"}, {"distance": {"text": "19 m", "value": 19}, "duration": {"text": "1 min", "value": 3}, "end_location": {"lat": 45.4172847, "lng": 11.9327696}, "html_instructions": "Keep <b>right</b> at the fork to continue toward <b>Via S. Marco</b>", "maneuver": "fork-right", "polyline": {"points": "cqetGitygABn@"}, "start_location": {"lat": 45.4173025, "lng": 11.9330073}, "travel_mode": "DRIVING"}, {"distance": {"text": "0.4 km", "value": 423}, "duration": {"text": "1 min", "value": 40}, "end_location": {"lat": 45.4195705, "lng": 11.9322249}, "html_instructions": "Keep <b>right</b>, follow signs for <b>Ponte di Brenta</b>", "maneuver": "keep-right", "polyline": {"points": "_qetGyrygAELADAF?H?\\CTABAFABAFKVUXo@z@ED[`@GFSVu@`A]f@OPOLIFKBK@K?E?EAIECCECEECECCCGEKAGEOIk@_@wBWaB"}, "start_location": {"lat": 45.4172847, "lng": 11.9327696}, "travel_mode": "DRIVING"}, {"distance": {"text": "0.4 km", "value": 377}, "duration": {"text": "1 min", "value": 28}, "end_location": {"lat": 45.4212032, "lng": 11.9363891}, "html_instructions": "Keep <b>left</b> at the fork, follow signs for <b>Vigonza</b> and merge onto <b>Via S. Marco</b>", "maneuver": "fork-left", "polyline": {"points": "i_ftGkoygAKUI[Gc@ScAMy@EQAG?CCEIQEq@Ii@G_@Kc@Ma@EISi@GQISIUIUOc@EMSi@Wo@_@y@[i@"}, "start_location": {"lat": 45.4195705, "lng": 11.9322249}, "travel_mode": "DRIVING"}, {"distance": {"text": "1.3 km", "value": 1273}, "duration": {"text": "2 mins", "value": 98}, "end_location": {"lat": 45.4166509, "lng": 11.9224319}, "html_instructions": "At the roundabout, take the <b>3rd</b> exit and stay on <b>Via S. Marco</b>", "maneuver": "roundabout-right", "polyline": {"points": "oiftGmizgA?A?A?A?A?AAA?A?A?AA??A?AA??AAAAAAAA?AAA?A?A?A?A?A@A??@A?A@A@?@A@?@?@A??@?@?@?@?@?@?@?@?@?@@@?@?@@@?@@@@@?@@??@@?@??@@?@?@?@?@?j@P^x@Vn@Rh@DLNb@HTHTHRFPRh@DHL`@Jb@F^Hh@Dp@Dj@Fp@@FDb@JdA\\xBj@~CRnAd@fCF^r@zDJr@R|@`@vAZfAf@jB\\lAf@nBb@|AFRRt@Pj@tBrHRv@Rr@?H?B@R@J?F?H?HCV"}, "start_location": {"lat": 45.4212032, "lng": 11.9363891}, "travel_mode": "DRIVING"}, {"distance": {"text": "0.2 km", "value": 216}, "duration": {"text": "1 min", "value": 21}, "end_location": {"lat": 45.4156369, "lng": 11.920241}, "html_instructions": "At the roundabout, take the <b>2nd</b> exit onto <b>Via S. Marco</b>/<b>Via Venezia</b>", "maneuver": "roundabout-right", "polyline": {"points": "ametGerwgACNAB?F@L?B@B@@@B@BB@@B@@BBDDD?F@LHDBDBDFDJJVHNXhAr@dCJ\\Nh@"}, "start_location": {"lat": 45.4166509, "lng": 11.9224319}, "travel_mode": "DRIVING"}, {"distance": {"text": "0.9 km", "value": 940}, "duration": {"text": "1 min", "value": 68}, "end_location": {"lat": 45.4116151, "lng": 11.909657}, "html_instructions": "Continue straight onto <b>Via Venezia</b>", "maneuver": "straight", "polyline": {"points": "wfetGodwgA\\dA\\nA`@xAr@fCtA~EPj@Pl@f@hBHT@FBHFRRx@l@tB@FDPPj@HVFVFVb@zAV|@|@|Ct@lCTx@J\\f@fBFd@FTvAjF"}, "start_location": {"lat": 45.4156369, "lng": 11.920241}, "travel_mode": "DRIVING"}, {"distance": {"text": "0.7 km", "value": 659}, "duration": {"text": "1 min", "value": 65}, "end_location": {"lat": 45.4087508, "lng": 11.9023439}, "html_instructions": "At the roundabout, take the <b>2nd</b> exit and stay on <b>Via Venezia</b>", "maneuver": "roundabout-right", "polyline": {"points": "smdtGkbugA?@A@?@A??@?@?@A??@?@?@?@?@?@?@?@@@?@X|@FPf@fBZfAPl@f@~AzEbPp@lB@@NTzArF`@zABN"}, "start_location": {"lat": 45.4116151, "lng": 11.909657}, "travel_mode": "DRIVING"}, {"distance": {"text": "0.5 km", "value": 475}, "duration": {"text": "1 min", "value": 66}, "end_location": {"lat": 45.4059187, "lng": 11.9010695}, "html_instructions": "At the roundabout, take the <b>4th</b> exit onto <b>Via Ludovico Ariosto</b><div style=\"font-size:0.9em\">Go through 1 roundabout</div>", "maneuver": "roundabout-right", "polyline": {"points": "u{ctGstsgAIBGDEFEDGFGDOFIDCHEJAFAD?HAH@JDR@HBFBFB@D@B?F?FADEHEBCj@g@LWJQRDD@HDBBLFTLf@Xb@XTLNH@?DDFDD@D@D@D?D?HE~@LZDj@H`@Fb@D^D^D"}, "start_location": {"lat": 45.4087508, "lng": 11.9023439}, "travel_mode": "DRIVING"}, {"distance": {"text": "71 m", "value": 71}, "duration": {"text": "1 min", "value": 7}, "end_location": {"lat": 45.4052838, "lng": 11.9009746}, "html_instructions": "Continue onto <b>Ponte Ariosto</b>", "polyline": {"points": "_jctGulsgAPBPBx@JN?B?L?"}, "start_location": {"lat": 45.4059187, "lng": 11.9010695}, "travel_mode": "DRIVING"}, {"distance": {"text": "0.2 km", "value": 250}, "duration": {"text": "1 min", "value": 27}, "end_location": {"lat": 45.4031285, "lng": 11.9000795}, "html_instructions": "At the roundabout, take the <b>2nd</b> exit onto <b>Via Ludovico Ariosto</b>", "maneuver": "roundabout-right", "polyline": {"points": "_fctGalsgA@??@@?@?@?@?@?@AfErAhCx@lAb@"}, "start_location": {"lat": 45.4052838, "lng": 11.9009746}, "travel_mode": "DRIVING"}, {"distance": {"text": "0.9 km", "value": 930}, "duration": {"text": "2 mins", "value": 110}, "end_location": {"lat": 45.40180760000001, "lng": 11.8893678}, "html_instructions": "At the roundabout, take the <b>1st</b> exit onto <b>Via Gattamelata</b><div style=\"font-size:0.9em\">Go through 1 roundabout</div>", "maneuver": "roundabout-right", "polyline": {"points": "qxbtGofsgA?@@??@@@@@CLAPOxA?ZEb@QrBMrAOz@I`@Mj@Of@[dA[~@GXCPCLAN?T?XB\\@RHt@h@|CLn@ZfBA??@A??@?@A??@?@?@A@?@?@@??@?@?@?@@??@?@@??@@?@@@?@?@?@??A@?Pt@HVTn@\\x@dA~BRf@FJ?L?@?@XdA`AxDFT\\nANr@DRDv@"}, "start_location": {"lat": 45.4031285, "lng": 11.9000795}, "travel_mode": "DRIVING"}, {"distance": {"text": "0.4 km", "value": 423}, "duration": {"text": "1 min", "value": 61}, "end_location": {"lat": 45.39875929999999, "lng": 11.8864392}, "html_instructions": "At the roundabout, take the <b>2nd</b> exit and stay on <b>Via Gattamelata</b>", "maneuver": "roundabout-right", "polyline": {"points": "ipbtGqcqgACL?@A@?@?@?@?@?@?@?@?@@@?@?@@@?@@@@@?@@??@@?@@@?@?@?@?@?@?@?LTFJPTHJXZB@B@F?^V~CvBhAv@h@`@r@f@t@r@X\\V\\^l@"}, "start_location": {"lat": 45.40180760000001, "lng": 11.8893678}, "travel_mode": "DRIVING"}, {"distance": {"text": "0.2 km", "value": 170}, "duration": {"text": "1 min", "value": 34}, "end_location": {"lat": 45.4000198, "lng": 11.8852931}, "html_instructions": "At the roundabout, take the <b>1st</b> exit onto <b>Via Jacopo Facciolati</b>", "maneuver": "roundabout-right", "polyline": {"points": "g}atGgqpgA?@A??@A??@?@A??@?@?@?@?@?@?@?@k@n@m@f@qAz@iAx@"}, "start_location": {"lat": 45.39875929999999, "lng": 11.8864392}, "travel_mode": "DRIVING"}, {"distance": {"text": "0.2 km", "value": 234}, "duration": {"text": "1 min", "value": 44}, "end_location": {"lat": 45.4016916, "lng": 11.8837932}, "html_instructions": "At the roundabout, take the <b>2nd</b> exit onto <b>Piazzale Pontecorvo</b>", "maneuver": "roundabout-right", "polyline": {"points": "cebtGajpgA?AA??AA??AA??AA?A?A?A?A??@A??@A??@A??@?@A??@?@?@?@?@?@?@MCEAQPCH[x@CJGLKLIHMJOLEFCHg@T}@j@]Ra@V"}, "start_location": {"lat": 45.4000198, "lng": 11.8852931}, "travel_mode": "DRIVING"}, {"distance": {"text": "0.1 km", "value": 98}, "duration": {"text": "1 min", "value": 20}, "end_location": {"lat": 45.4024941, "lng": 11.8832767}, "html_instructions": "Continue onto <b>Via S. Francesco</b>", "polyline": {"points": "qobtGu`pgAg@Z_@TwAr@"}, "start_location": {"lat": 45.4016916, "lng": 11.8837932}, "travel_mode": "DRIVING"}, {"distance": {"text": "0.2 km", "value": 199}, "duration": {"text": "1 min", "value": 42}, "end_location": {"lat": 45.4019556, "lng": 11.8808685}, "html_instructions": "<b>Via S. Francesco</b> turns <b>left</b> and becomes <b>Via M. Cesarotti</b>", "polyline": {"points": "qtbtGo}ogAAH?F?B@HDPZvALh@T`AF^Bf@Dl@Dh@J~@?J"}, "start_location": {"lat": 45.4024941, "lng": 11.8832767}, "travel_mode": "DRIVING"}, {"distance": {"text": "71 m", "value": 71}, "duration": {"text": "1 min", "value": 18}, "end_location": {"lat": 45.4018179, "lng": 11.8799761}, "html_instructions": "Continue onto <b>Piazza del Santo</b>", "polyline": {"points": "gqbtGmnogALvAD`@Fv@"}, "start_location": {"lat": 45.4019556, "lng": 11.8808685}, "travel_mode": "DRIVING"}, {"distance": {"text": "0.2 km", "value": 172}, "duration": {"text": "1 min", "value": 41}, "end_location": {"lat": 45.4032502, "lng": 11.8791555}, "html_instructions": "Turn <b>right</b> onto <b>Via del Santo</b><div style=\"font-size:0.9em\">Closed Mon\u2013Fri 8:00 AM \u2013 8:00 PM</div>", "maneuver": "turn-right", "polyline": {"points": "kpbtG{hogAi@Pk@Tc@Ta@N_@TKDa@Vs@`@"}, "start_location": {"lat": 45.4018179, "lng": 11.8799761}, "travel_mode": "DRIVING"}, {"distance": {"text": "71 m", "value": 71}, "duration": {"text": "1 min", "value": 20}, "end_location": {"lat": 45.4027221, "lng": 11.8786352}, "html_instructions": "Turn <b>left</b> onto <b>Via Rudena</b><div style=\"font-size:0.9em\">Entering toll zone</div>", "maneuver": "turn-left", "polyline": {"points": "iybtGwcogAhBfB"}, "start_location": {"lat": 45.4032502, "lng": 11.8791555}, "travel_mode": "DRIVING"}, {"distance": {"text": "0.2 km", "value": 222}, "duration": {"text": "1 min", "value": 67}, "end_location": {"lat": 45.4033892, "lng": 11.876246}, "html_instructions": "Turn <b>right</b> onto <b>Via Santa Chiara</b><div style=\"font-size:0.9em\">Leaving toll zone</div>", "maneuver": "turn-right", "polyline": {"points": "_vbtGo`ogAk@pB?BA?A@A?A?A?CAA?A?A?A@?@ABCDADCJABIXQt@IZGXG\\Mt@NF?@@??@@@?B@D?DAJAPCl@"}, "start_location": {"lat": 45.4027221, "lng": 11.8786352}, "travel_mode": "DRIVING"}, {"distance": {"text": "0.3 km", "value": 337}, "duration": {"text": "1 min", "value": 87}, "end_location": {"lat": 45.4061723, "lng": 11.8778065}, "html_instructions": "Turn <b>right</b> onto <b>Riviera Tito Livio</b><div style=\"font-size:0.9em\">Entering toll zone</div>", "maneuver": "turn-right", "polyline": {"points": "ezbtGqqngAMJK?EAGACCWQeA{@QIg@WQIuAe@u@]k@YaAg@SMGGQKm@Y"}, "start_location": {"lat": 45.4033892, "lng": 11.876246}, "travel_mode": "DRIVING"}, {"distance": {"text": "85 m", "value": 85}, "duration": {"text": "1 min", "value": 33}, "end_location": {"lat": 45.406418, "lng": 11.8767801}, "html_instructions": "Turn <b>left</b> onto <b>Via S. Francesco</b>", "maneuver": "turn-left", "polyline": {"points": "qkctGi{ngAq@lE"}, "start_location": {"lat": 45.4061723, "lng": 11.8778065}, "travel_mode": "DRIVING"}], "traffic_speed_entry": [], "via_waypoint": []}], "overview_polyline": {"points": "eniuGijgiAZe@p@sGn@wUt@c^VgHn@{Bh@uAvCcFt]}j@d@kCl@kKxA}UpAoFpBcH|AiMzCeWtDy\\FuAGuCWkBk@{BaC_HUmADuAHGFKH_@?_@CMbCiEbAyBl@cCXsCBgBY{FAmBh@oCz@oAbBu@v@Y|@q@t@yAXiCGaDDkCh@yCpAsCxB}BjB_AfA[hEu@`BaAhCyCfB{@rDYL^VLXKJ_@Ac@Di@jAoCdCqA`Bs@~FqEjCqAtZeDnCMbA`@h@r@ZjAB|AUbCk@pC[h@mAn@}@OIM]SSa@Mw@BsMByCNeM@y@ROXy@Bm@Y{@WeBh@iITaUZgL`@_@Fw@Uo@SKEsF|@{y@LgGZuDdA{E`A}BdAeBvBeCfEqD~DsCp@SFJTJn@GX]L}AUs@EyAN{BhA{LNcLO}Gu@mLGqEJ{En@gC|@eAn@Y`BGxCHzJX`FZfFXtNt@fRbA|`@xBdUfA|D@bGWfJgAzHwBjB[vHgChKiD`Dq@`EInDLtBCzALt@\\dBjB\\XnG|NnDhIjNz[~HhQ|KhTxMhUlQvZzG`MnHnOjEjKnElJvNlXz@zA`DpEzExD~S|K~MbHjElB|ExApPtEzCxAdEvCtDfEjOvSnLvObDzCrE|CdEhBzIzB|UjFjHpB|]hQlDbCdCdDvB|E|A|Gf@tF~@vNjBrPjHhj@nCzWlBrLvMlfApOhpAbv@jlGfa@dfDfBfObBvQzCxWFdBKtCOzBCpC`@hDtE|NjAdFn@zD\\`Az@vGfAfJ~ApMtCzU`Fha@fJtu@lhBz~NfMbeAlHrj@~Ijt@n@jFz@nJ?jC[xDqDfM@xAXlA`AnA|@^pEzAp@f@j@|@dA`Gb@~If@|Dh@fDQdBe@|@yAjBwBrCq@Za@GSSwAuHgAmF_A}EoAiDmBmECQWIKZNXD?l@PpA`DhA~Cf@nB\\xDp@jFlBvKtBdKhCpJnF|RCfBFj@l@\\VZbBvFtGjUbGjTtCbKnCnKADCLjAbEpHxV~CxJd@jBQH[Zc@b@E`@Lp@PJ^MhAuAvCzAfAh@tAFlC\\~D^@@F?hLvD{@`Kw@pDcApDElAx@dGf@xCCDAFDNJ@r@zB~BlFXvAvBrIFxAAJBPLHF?tAbBpGfElDzCt@lACF?F?Dk@n@iEzCAACAEAE@EL?D?@SEUZs@`Bm@j@gC~AaE|BdAtFv@dJFv@i@PoAj@oBbAs@`@hBfBk@tBG@M@s@jCOv@Mt@NF@@?@BJGpAg@FsB{AeEeBiCwA_Ae@q@lE"}, "summary": "Tangenziale di Mestre", "warnings": [], "waypoint_order": []}], "status": "OK"}